django_pg_zero_downtime_migrations-0.19.dist-info/licenses/AUTHORS
django_pg_zero_downtime_migrations-0.19.dist-info/licenses/LICENSE
django_zero_downtime_migrations/__init__.py
django_zero_downtime_migrations/backends/__init__.py
django_zero_downtime_migrations/backends/postgis/__init__.py
django_zero_downtime_migrations/backends/postgis/base.py
django_zero_downtime_migrations/backends/postgis/schema.py
django_zero_downtime_migrations/backends/postgres/__init__.py
django_zero_downtime_migrations/backends/postgres/base.py
django_zero_downtime_migrations/backends/postgres/schema.py
django_pg_zero_downtime_migrations-0.19.dist-info/METADATA
django_pg_zero_downtime_migrations-0.19.dist-info/WHEEL
django_pg_zero_downtime_migrations-0.19.dist-info/top_level.txt
django_pg_zero_downtime_migrations-0.19.dist-info/RECORD
